ShieldedPy/__init__.py
ShieldedPy/security.py
ShieldedPy-1.0.0.dist-info/LICENSE
ShieldedPy-1.0.0.dist-info/METADATA
ShieldedPy-1.0.0.dist-info/WHEEL
ShieldedPy-1.0.0.dist-info/top_level.txt
ShieldedPy-1.0.0.dist-info/RECORD
