Metadata-Version: 2.1
Name: ShieldedPy
Version: 1.0.0
Summary: A simple library for security tasks like password hashing, token management, and encryption.
Home-page: https://github.com/tamilsud/ShieldedPy
Author: Tamilselvan Sudalai
Author-email: tamil.sdl@gmail.com
Classifier: Programming Language :: Python :: 3
Classifier: License :: OSI Approved :: MIT License
Classifier: Operating System :: OS Independent
Requires-Python: >=3.6
License-File: LICENSE
Requires-Dist: cryptography
Requires-Dist: PyJWT
Requires-Dist: passlib
